{
  "DocumentMetadata": {
    "Pages": 1
  },
  "ExpenseDocuments": [
    {
      "ExpenseIndex": 1,
      "SummaryFields": [
        {
          "Type": {
            "Text": "VENDOR_NAME",
            "Confidence": 97.81664276123047
          },
          "ValueDetection": {
            "Text": "CVS pharmacy R",
            "Geometry": {
              "BoundingBox": {
                "Width": 0.27688679099082947,
                "Height": 0.02866666577756405,
                "Left": 0.42783018946647644,
                "Top": 0.1706666648387909
              },
              "Polygon": [
                {
                  "X": 0.42783018946647644,
                  "Y": 0.1706666648387909
                },
                {
                  "X": 0.7047169804573059,
                  "Y": 0.1706666648387909
                },
                {
                  "X": 0.7047169804573059,
                  "Y": 0.1993333399295807
                },
                {
                  "X": 0.42783018946647644,
                  "Y": 0.1993333399295807
                }
              ]
            },
            "Confidence": 93.3287353515625
          },
          "PageNumber": 1
        },
        {
          "Type": {
            "Text": "OTHER",
            "Confidence": 56.0
          },
          "LabelDetection": {
            "Text": "CHANGE",
            "Geometry": {
              "BoundingBox": {
                "Width": 0.04100482910871506,
                "Height": 0.009511596523225307,
                "Left": 0.43834254145622253,
                "Top": 0.45588627457618713
              },
              "Polygon": [
                {
                  "X": 0.43834254145622253,
                  "Y": 0.45588627457618713
                },
                {
                  "X": 0.4793473780155182,
                  "Y": 0.45588627457618713
                },
                {
                  "X": 0.4793473780155182,
                  "Y": 0.4653978645801544
                },
                {
                  "X": 0.43834254145622253,
                  "Y": 0.4653978645801544
                }
              ]
            },
            "Confidence": 55.98503494262695
          },
          "ValueDetection": {
            "Text": ".00",
            "Geometry": {
              "BoundingBox": {
                "Width": 0.017030708491802216,
                "Height": 0.00933862291276455,
                "Left": 0.619871199131012,
                "Top": 0.4547381103038788
              },
              "Polygon": [
                {
                  "X": 0.619871199131012,
                  "Y": 0.4547381103038788
                },
                {
                  "X": 0.6369019150733948,
                  "Y": 0.4547381103038788
                },
                {
                  "X": 0.6369019150733948,
                  "Y": 0.4640767276287079
                },
                {
                  "X": 0.619871199131012,
                  "Y": 0.4640767276287079
                }
              ]
            },
            "Confidence": 55.731956481933594
          },
          "PageNumber": 1
        },
        {
          "Type": {
            "Text": "OTHER",
            "Confidence": 44.0
          },
          "LabelDetection": {
            "Text": "TRAN TYPE SALE",
            "Geometry": {
              "BoundingBox": {
                "Width": 0.10037001222372055,
                "Height": 0.01018644217401743,
                "Left": 0.39323246479034424,
                "Top": 0.4098395109176636
              },
              "Polygon": [
                {
                  "X": 0.39323246479034424,
                  "Y": 0.4098395109176636
                },
                {
                  "X": 0.4936024844646454,
                  "Y": 0.4098395109176636
                },
                {
                  "X": 0.4936024844646454,
                  "Y": 0.4200259745121002
                },
                {
                  "X": 0.39323246479034424,
                  "Y": 0.4200259745121002
                }
              ]
            },
            "Confidence": 43.958431243896484
          },
          "ValueDetection": {
            "Text": "A0000000031010",
            "Geometry": {
              "BoundingBox": {
                "Width": 0.09409323334693909,
                "Height": 0.010292398743331432,
                "Left": 0.6068602204322815,
                "Top": 0.4085550904273987
              },
              "Polygon": [
                {
                  "X": 0.6068602204322815,
                  "Y": 0.4085550904273987
                },
                {
                  "X": 0.700953483581543,
                  "Y": 0.4085550904273987
                },
                {
                  "X": 0.700953483581543,
                  "Y": 0.4188475012779236
                },
                {
                  "X": 0.6068602204322815,
                  "Y": 0.4188475012779236
                }
              ]
            },
            "Confidence": 43.960426330566406
          },
          "PageNumber": 1
        },
        {
          "Type": {
            "Text": "OTHER",
            "Confidence": 42.5
          },
          "LabelDetection": {
            "Text": "APPROVED# 005234",
            "Geometry": {
              "BoundingBox": {
                "Width": 0.10419020801782608,
                "Height": 0.00972110964357853,
                "Left": 0.39300310611724854,
                "Top": 0.40125325322151184
              },
              "Polygon": [
                {
                  "X": 0.39300310611724854,
                  "Y": 0.40125325322151184
                },
                {
                  "X": 0.497193306684494,
                  "Y": 0.40125325322151184
                },
                {
                  "X": 0.497193306684494,
                  "Y": 0.4109743535518646
                },
                {
                  "X": 0.39300310611724854,
                  "Y": 0.4109743535518646
                }
              ]
            },
            "Confidence": 42.454044342041016
          },
          "ValueDetection": {
            "Text": "REF# 181327",
            "Geometry": {
              "BoundingBox": {
                "Width": 0.07091536372900009,
                "Height": 0.009890462271869183,
                "Left": 0.568259596824646,
                "Top": 0.3993508219718933
              },
              "Polygon": [
                {
                  "X": 0.568259596824646,
                  "Y": 0.3993508219718933
                },
                {
                  "X": 0.6391749382019043,
                  "Y": 0.3993508219718933
                },
                {
                  "X": 0.6391749382019043,
                  "Y": 0.40924128890037537
                },
                {
                  "X": 0.568259596824646,
                  "Y": 0.40924128890037537
                }
              ]
            },
            "Confidence": 42.182952880859375
          },
          "PageNumber": 1
        },
        {
          "Type": {
            "Text": "OTHER",
            "Confidence": 40.5
          },
          "LabelDetection": {
            "Text": "CHARGE",
            "Geometry": {
              "BoundingBox": {
                "Width": 0.03927068039774895,
                "Height": 0.010595906525850296,
                "Left": 0.4383871257305145,
                "Top": 0.37285953760147095
              },
              "Polygon": [
                {
                  "X": 0.4383871257305145,
                  "Y": 0.37285953760147095
                },
                {
                  "X": 0.47765782475471497,
                  "Y": 0.37285953760147095
                },
                {
                  "X": 0.47765782475471497,
                  "Y": 0.38345545530319214
                },
                {
                  "X": 0.4383871257305145,
                  "Y": 0.38345545530319214
                }
              ]
            },
            "Confidence": 40.47855758666992
          },
          "ValueDetection": {
            "Text": "16.76",
            "Geometry": {
              "BoundingBox": {
                "Width": 0.03372422605752945,
                "Height": 0.009293782524764538,
                "Left": 0.6016968488693237,
                "Top": 0.373493492603302
              },
              "Polygon": [
                {
                  "X": 0.6016968488693237,
                  "Y": 0.373493492603302
                },
                {
                  "X": 0.6354210376739502,
                  "Y": 0.373493492603302
                },
                {
                  "X": 0.6354210376739502,
                  "Y": 0.3827872574329376
                },
                {
                  "X": 0.6016968488693237,
                  "Y": 0.3827872574329376
                }
              ]
            },
            "Confidence": 39.26899719238281
          },
          "PageNumber": 1
        },
        {
          "Type": {
            "Text": "OTHER",
            "Confidence": 40.0
          },
          "LabelDetection": {
            "Text": "************6957",
            "Geometry": {
              "BoundingBox": {
                "Width": 0.10566677153110504,
                "Height": 0.007649210747331381,
                "Left": 0.43769198656082153,
                "Top": 0.38354989886283875
              },
              "Polygon": [
                {
                  "X": 0.43769198656082153,
                  "Y": 0.38354989886283875
                },
                {
                  "X": 0.5433587431907654,
                  "Y": 0.38354989886283875
                },
                {
                  "X": 0.5433587431907654,
                  "Y": 0.3911990821361542
                },
                {
                  "X": 0.43769198656082153,
                  "Y": 0.3911990821361542
                }
              ]
            },
            "Confidence": 32.185726165771484
          },
          "ValueDetection": {
            "Text": "CH",
            "Geometry": {
              "BoundingBox": {
                "Width": 0.011814218014478683,
                "Height": 0.007414184510707855,
                "Left": 0.5890226364135742,
                "Top": 0.38237279653549194
              },
              "Polygon": [
                {
                  "X": 0.5890226364135742,
                  "Y": 0.38237279653549194
                },
                {
                  "X": 0.6008368730545044,
                  "Y": 0.38237279653549194
                },
                {
                  "X": 0.6008368730545044,
                  "Y": 0.3897869884967804
                },
                {
                  "X": 0.5890226364135742,
                  "Y": 0.3897869884967804
                }
              ]
            },
            "Confidence": 39.20758056640625
          },
          "PageNumber": 1
        },
        {
          "Type": {
            "Text": "OTHER",
            "Confidence": 37.0
          },
          "LabelDetection": {
            "Text": "NO SIGNATURE REQUIRED",
            "Geometry": {
              "BoundingBox": {
                "Width": 0.13913646340370178,
                "Height": 0.009987751953303814,
                "Left": 0.39237454533576965,
                "Top": 0.42751196026802063
              },
              "Polygon": [
                {
                  "X": 0.39237454533576965,
                  "Y": 0.42751196026802063
                },
                {
                  "X": 0.5315110087394714,
                  "Y": 0.42751196026802063
                },
                {
                  "X": 0.5315110087394714,
                  "Y": 0.4374997019767761
                },
                {
                  "X": 0.39237454533576965,
                  "Y": 0.4374997019767761
                }
              ]
            },
            "Confidence": 36.936073303222656
          },
          "ValueDetection": {
            "Text": "CVM: 5E0000",
            "Geometry": {
              "BoundingBox": {
                "Width": 0.07366234809160233,
                "Height": 0.00920544471591711,
                "Left": 0.5687709450721741,
                "Top": 0.42700955271720886
              },
              "Polygon": [
                {
                  "X": 0.5687709450721741,
                  "Y": 0.42700955271720886
                },
                {
                  "X": 0.6424332857131958,
                  "Y": 0.42700955271720886
                },
                {
                  "X": 0.6424332857131958,
                  "Y": 0.43621501326560974
                },
                {
                  "X": 0.5687709450721741,
                  "Y": 0.43621501326560974
                }
              ]
            },
            "Confidence": 36.963314056396484
          },
          "PageNumber": 1
        },
        {
          "Type": {
            "Text": "OTHER",
            "Confidence": 29.0
          },
          "LabelDetection": {
            "Text": "TC: 38FEOF858207E942",
            "Geometry": {
              "BoundingBox": {
                "Width": 0.1318269819021225,
                "Height": 0.009699340909719467,
                "Left": 0.39342302083969116,
                "Top": 0.41848406195640564
              },
              "Polygon": [
                {
                  "X": 0.39342302083969116,
                  "Y": 0.41848406195640564
                },
                {
                  "X": 0.5252500176429749,
                  "Y": 0.41848406195640564
                },
                {
                  "X": 0.5252500176429749,
                  "Y": 0.428183376789093
                },
                {
                  "X": 0.39342302083969116,
                  "Y": 0.428183376789093
                }
              ]
            },
            "Confidence": 28.29816436767578
          },
          "ValueDetection": {
            "Text": "TERMINAL# 05042654",
            "Geometry": {
              "BoundingBox": {
                "Width": 0.11726805567741394,
                "Height": 0.01066068559885025,
                "Left": 0.5703654885292053,
                "Top": 0.41774362325668335
              },
              "Polygon": [
                {
                  "X": 0.5703654885292053,
                  "Y": 0.41774362325668335
                },
                {
                  "X": 0.6876335144042969,
                  "Y": 0.41774362325668335
                },
                {
                  "X": 0.6876335144042969,
                  "Y": 0.428404301404953
                },
                {
                  "X": 0.5703654885292053,
                  "Y": 0.428404301404953
                }
              ]
            },
            "Confidence": 28.966068267822266
          },
          "PageNumber": 1
        },
        {
          "Type": {
            "Text": "OTHER",
            "Confidence": 24.5
          },
          "LabelDetection": {
            "Text": "TSI(9B):",
            "Geometry": {
              "BoundingBox": {
                "Width": 0.05481337010860443,
                "Height": 0.009074178524315357,
                "Left": 0.5702009797096252,
                "Top": 0.43604016304016113
              },
              "Polygon": [
                {
                  "X": 0.5702009797096252,
                  "Y": 0.43604016304016113
                },
                {
                  "X": 0.6250143647193909,
                  "Y": 0.43604016304016113
                },
                {
                  "X": 0.6250143647193909,
                  "Y": 0.4451143443584442
                },
                {
                  "X": 0.5702009797096252,
                  "Y": 0.4451143443584442
                }
              ]
            },
            "Confidence": 24.20364761352539
          },
          "ValueDetection": {
            "Text": "6800",
            "Geometry": {
              "BoundingBox": {
                "Width": 0.028248682618141174,
                "Height": 0.009272867813706398,
                "Left": 0.6274130344390869,
                "Top": 0.43612992763519287
              },
              "Polygon": [
                {
                  "X": 0.6274130344390869,
                  "Y": 0.43612992763519287
                },
                {
                  "X": 0.6556617021560669,
                  "Y": 0.43612992763519287
                },
                {
                  "X": 0.6556617021560669,
                  "Y": 0.4454028010368347
                },
                {
                  "X": 0.6274130344390869,
                  "Y": 0.4454028010368347
                }
              ]
            },
            "Confidence": 24.24204444885254
          },
          "PageNumber": 1
        },
        {
          "Type": {
            "Text": "OTHER",
            "Confidence": 22.0
          },
          "LabelDetection": {
            "Text": "Health Care Eligible Total",
            "Geometry": {
              "BoundingBox": {
                "Width": 0.23120759427547455,
                "Height": 0.010066243819892406,
                "Left": 0.39327868819236755,
                "Top": 0.6317192912101746
              },
              "Polygon": [
                {
                  "X": 0.39327868819236755,
                  "Y": 0.6317192912101746
                },
                {
                  "X": 0.6244862675666809,
                  "Y": 0.6317192912101746
                },
                {
                  "X": 0.6244862675666809,
                  "Y": 0.6417855024337769
                },
                {
                  "X": 0.39327868819236755,
                  "Y": 0.6417855024337769
                }
              ]
            },
            "Confidence": 21.956832885742188
          },
          "ValueDetection": {
            "Text": "16.76",
            "Geometry": {
              "BoundingBox": {
                "Width": 0.04261371120810509,
                "Height": 0.009573160670697689,
                "Left": 0.6520521640777588,
                "Top": 0.6305385828018188
              },
              "Polygon": [
                {
                  "X": 0.6520521640777588,
                  "Y": 0.6305385828018188
                },
                {
                  "X": 0.6946658492088318,
                  "Y": 0.6305385828018188
                },
                {
                  "X": 0.6946658492088318,
                  "Y": 0.6401117444038391
                },
                {
                  "X": 0.6520521640777588,
                  "Y": 0.6401117444038391
                }
              ]
            },
            "Confidence": 21.839374542236328
          },
          "PageNumber": 1
        },
        {
          "Type": {
            "Text": "OTHER",
            "Confidence": 22.0
          },
          "LabelDetection": {
            "Text": "7294 9880",
            "Geometry": {
              "BoundingBox": {
                "Width": 0.09572192281484604,
                "Height": 0.01841912791132927,
                "Left": 0.42377108335494995,
                "Top": 0.31587687134742737
              },
              "Polygon": [
                {
                  "X": 0.42377108335494995,
                  "Y": 0.31587687134742737
                },
                {
                  "X": 0.519493043422699,
                  "Y": 0.31587687134742737
                },
                {
                  "X": 0.519493043422699,
                  "Y": 0.33429598808288574
                },
                {
                  "X": 0.42377108335494995,
                  "Y": 0.33429598808288574
                }
              ]
            },
            "Confidence": 20.43260955810547
          },
          "ValueDetection": {
            "Text": "432 73",
            "Geometry": {
              "BoundingBox": {
                "Width": 0.06463715434074402,
                "Height": 0.019811442121863365,
                "Left": 0.5836973786354065,
                "Top": 0.3139970898628235
              },
              "Polygon": [
                {
                  "X": 0.5836973786354065,
                  "Y": 0.3139970898628235
                },
                {
                  "X": 0.6483345627784729,
                  "Y": 0.3139970898628235
                },
                {
                  "X": 0.6483345627784729,
                  "Y": 0.3338085412979126
                },
                {
                  "X": 0.5836973786354065,
                  "Y": 0.3338085412979126
                }
              ]
            },
            "Confidence": 20.98263168334961
          },
          "PageNumber": 1
        },
        {
          "Type": {
            "Text": "TOTAL",
            "Confidence": 98.85694122314453
          },
          "LabelDetection": {
            "Text": "TOTAL",
            "Geometry": {
              "BoundingBox": {
                "Width": 0.033018868416547775,
                "Height": 0.008666666224598885,
                "Left": 0.4372641444206238,
                "Top": 0.36500000953674316
              },
              "Polygon": [
                {
                  "X": 0.4372641444206238,
                  "Y": 0.36500000953674316
                },
                {
                  "X": 0.47028303146362305,
                  "Y": 0.36500000953674316
                },
                {
                  "X": 0.47028303146362305,
                  "Y": 0.3736666738986969
                },
                {
                  "X": 0.4372641444206238,
                  "Y": 0.3736666738986969
                }
              ]
            },
            "Confidence": 98.78424072265625
          },
          "ValueDetection": {
            "Text": "16.76",
            "Geometry": {
              "BoundingBox": {
                "Width": 0.033018868416547775,
                "Height": 0.009333333000540733,
                "Left": 0.600943386554718,
                "Top": 0.3633333444595337
              },
              "Polygon": [
                {
                  "X": 0.600943386554718,
                  "Y": 0.3633333444595337
                },
                {
                  "X": 0.6339622735977173,
                  "Y": 0.3633333444595337
                },
                {
                  "X": 0.6339622735977173,
                  "Y": 0.3726666569709778
                },
                {
                  "X": 0.600943386554718,
                  "Y": 0.3726666569709778
                }
              ]
            },
            "Confidence": 97.2930908203125
          },
          "PageNumber": 1
        },
        {
          "Type": {
            "Text": "SUBTOTAL",
            "Confidence": 99.70035552978516
          },
          "LabelDetection": {
            "Text": "SUBTOTAL",
            "Geometry": {
              "BoundingBox": {
                "Width": 0.052358489483594894,
                "Height": 0.008999999612569809,
                "Left": 0.4367924630641937,
                "Top": 0.34599998593330383
              },
              "Polygon": [
                {
                  "X": 0.4367924630641937,
                  "Y": 0.34599998593330383
                },
                {
                  "X": 0.4891509413719177,
                  "Y": 0.34599998593330383
                },
                {
                  "X": 0.4891509413719177,
                  "Y": 0.35499998927116394
                },
                {
                  "X": 0.4367924630641937,
                  "Y": 0.35499998927116394
                }
              ]
            },
            "Confidence": 99.46804809570312
          },
          "ValueDetection": {
            "Text": "15.28",
            "Geometry": {
              "BoundingBox": {
                "Width": 0.034433960914611816,
                "Height": 0.009333333000540733,
                "Left": 0.6000000238418579,
                "Top": 0.34466665983200073
              },
              "Polygon": [
                {
                  "X": 0.6000000238418579,
                  "Y": 0.34466665983200073
                },
                {
                  "X": 0.6344339847564697,
                  "Y": 0.34466665983200073
                },
                {
                  "X": 0.6344339847564697,
                  "Y": 0.3540000021457672
                },
                {
                  "X": 0.6000000238418579,
                  "Y": 0.3540000021457672
                }
              ]
            },
            "Confidence": 97.7388687133789
          },
          "PageNumber": 1
        },
        {
          "Type": {
            "Text": "TAX",
            "Confidence": 95.7825698852539
          },
          "LabelDetection": {
            "Text": "MO 9.679% TAX",
            "Geometry": {
              "BoundingBox": {
                "Width": 0.08632075786590576,
                "Height": 0.009333333000540733,
                "Left": 0.4367924630641937,
                "Top": 0.35466668009757996
              },
              "Polygon": [
                {
                  "X": 0.4367924630641937,
                  "Y": 0.35466668009757996
                },
                {
                  "X": 0.5231131911277771,
                  "Y": 0.35466668009757996
                },
                {
                  "X": 0.5231131911277771,
                  "Y": 0.36399999260902405
                },
                {
                  "X": 0.4367924630641937,
                  "Y": 0.36399999260902405
                }
              ]
            },
            "Confidence": 93.14424133300781
          },
          "ValueDetection": {
            "Text": "1.48",
            "Geometry": {
              "BoundingBox": {
                "Width": 0.026886792853474617,
                "Height": 0.008666666224598885,
                "Left": 0.6066038012504578,
                "Top": 0.3540000021457672
              },
              "Polygon": [
                {
                  "X": 0.6066038012504578,
                  "Y": 0.3540000021457672
                },
                {
                  "X": 0.6334905624389648,
                  "Y": 0.3540000021457672
                },
                {
                  "X": 0.6334905624389648,
                  "Y": 0.36266666650772095
                },
                {
                  "X": 0.6066038012504578,
                  "Y": 0.36266666650772095
                }
              ]
            },
            "Confidence": 93.44380187988281
          },
          "PageNumber": 1
        }
      ],
      "LineItemGroups": [
        {
          "LineItemGroupIndex": 1,
          "LineItems": [
            {
              "LineItemExpenseFields": [
                {
                  "Type": {
                    "Text": "ITEM",
                    "Confidence": 90.21563720703125
                  },
                  "ValueDetection": {
                    "Text": "CVS H/C PATCH XL",
                    "Geometry": {
                      "BoundingBox": {
                        "Width": 0.12219037115573883,
                        "Height": 0.010079529136419296,
                        "Left": 0.4010591208934784,
                        "Top": 0.2656943202018738
                      },
                      "Polygon": [
                        {
                          "X": 0.4010591208934784,
                          "Y": 0.2656943202018738
                        },
                        {
                          "X": 0.5232495069503784,
                          "Y": 0.2656943202018738
                        },
                        {
                          "X": 0.5232495069503784,
                          "Y": 0.2757738530635834
                        },
                        {
                          "X": 0.4010591208934784,
                          "Y": 0.2757738530635834
                        }
                      ]
                    },
                    "Confidence": 90.1035385131836
                  },
                  "PageNumber": 1
                },
                {
                  "Type": {
                    "Text": "PRICE",
                    "Confidence": 90.21563720703125
                  },
                  "ValueDetection": {
                    "Text": "8.29T",
                    "Geometry": {
                      "BoundingBox": {
                        "Width": 0.03978288918733597,
                        "Height": 0.008063619025051594,
                        "Left": 0.599973738193512,
                        "Top": 0.2656943202018738
                      },
                      "Polygon": [
                        {
                          "X": 0.599973738193512,
                          "Y": 0.2656943202018738
                        },
                        {
                          "X": 0.6397566199302673,
                          "Y": 0.2656943202018738
                        },
                        {
                          "X": 0.6397566199302673,
                          "Y": 0.2737579345703125
                        },
                        {
                          "X": 0.599973738193512,
                          "Y": 0.2737579345703125
                        }
                      ]
                    },
                    "Confidence": 89.49711608886719
                  },
                  "PageNumber": 1
                },
                {
                  "Type": {
                    "Text": "QUANTITY",
                    "Confidence": 90.21563720703125
                  },
                  "ValueDetection": {
                    "Text": "F 1",
                    "Geometry": {
                      "BoundingBox": {
                        "Width": 0.021312296390533447,
                        "Height": 0.008063619025051594,
                        "Left": 0.3698010742664337,
                        "Top": 0.2667022943496704
                      },
                      "Polygon": [
                        {
                          "X": 0.3698010742664337,
                          "Y": 0.2667022943496704
                        },
                        {
                          "X": 0.39111337065696716,
                          "Y": 0.2667022943496704
                        },
                        {
                          "X": 0.39111337065696716,
                          "Y": 0.27476590871810913
                        },
                        {
                          "X": 0.3698010742664337,
                          "Y": 0.27476590871810913
                        }
                      ]
                    },
                    "Confidence": 78.92953491210938
                  },
                  "PageNumber": 1
                },
                {
                  "Type": {
                    "Text": "EXPENSE_ROW",
                    "Confidence": 90.21563720703125
                  },
                  "ValueDetection": {
                    "Text": "F 1 CVS H/C PATCH XL 3CT 8.29T",
                    "Geometry": {
                      "BoundingBox": {
                        "Width": 0.2870054244995117,
                        "Height": 0.012599426321685314,
                        "Left": 0.3690906763076782,
                        "Top": 0.2631744146347046
                      },
                      "Polygon": [
                        {
                          "X": 0.3690906763076782,
                          "Y": 0.2631744146347046
                        },
                        {
                          "X": 0.6560961008071899,
                          "Y": 0.2631744146347046
                        },
                        {
                          "X": 0.6560961008071899,
                          "Y": 0.2757738530635834
                        },
                        {
                          "X": 0.3690906763076782,
                          "Y": 0.2757738530635834
                        }
                      ]
                    },
                    "Confidence": 87.09635162353516
                  },
                  "PageNumber": 1
                }
              ]
            },
            {
              "LineItemExpenseFields": [
                {
                  "Type": {
                    "Text": "ITEM",
                    "Confidence": 78.50700378417969
                  },
                  "ValueDetection": {
                    "Text": "CVS H/C PATCH SM",
                    "Geometry": {
                      "BoundingBox": {
                        "Width": 0.12380045652389526,
                        "Height": 0.009818053804337978,
                        "Left": 0.4004769027233124,
                        "Top": 0.275200754404068
                      },
                      "Polygon": [
                        {
                          "X": 0.4004769027233124,
                          "Y": 0.275200754404068
                        },
                        {
                          "X": 0.52427738904953,
                          "Y": 0.275200754404068
                        },
                        {
                          "X": 0.52427738904953,
                          "Y": 0.28501880168914795
                        },
                        {
                          "X": 0.4004769027233124,
                          "Y": 0.28501880168914795
                        }
                      ]
                    },
                    "Confidence": 78.41693115234375
                  },
                  "PageNumber": 1
                },
                {
                  "Type": {
                    "Text": "PRICE",
                    "Confidence": 78.50700378417969
                  },
                  "ValueDetection": {
                    "Text": "6.99T",
                    "Geometry": {
                      "BoundingBox": {
                        "Width": 0.038420941680669785,
                        "Height": 0.008836262859404087,
                        "Left": 0.6011190414428711,
                        "Top": 0.275200754404068
                      },
                      "Polygon": [
                        {
                          "X": 0.6011190414428711,
                          "Y": 0.275200754404068
                        },
                        {
                          "X": 0.6395399570465088,
                          "Y": 0.275200754404068
                        },
                        {
                          "X": 0.6395399570465088,
                          "Y": 0.2840369939804077
                        },
                        {
                          "X": 0.6011190414428711,
                          "Y": 0.2840369939804077
                        }
                      ]
                    },
                    "Confidence": 78.41191101074219
                  },
                  "PageNumber": 1
                },
                {
                  "Type": {
                    "Text": "QUANTITY",
                    "Confidence": 78.50700378417969
                  },
                  "ValueDetection": {
                    "Text": "1",
                    "Geometry": {
                      "BoundingBox": {
                        "Width": 0.009960966184735298,
                        "Height": 0.008836262859404087,
                        "Left": 0.38197797536849976,
                        "Top": 0.27618253231048584
                      },
                      "Polygon": [
                        {
                          "X": 0.38197797536849976,
                          "Y": 0.27618253231048584
                        },
                        {
                          "X": 0.3919389545917511,
                          "Y": 0.27618253231048584
                        },
                        {
                          "X": 0.3919389545917511,
                          "Y": 0.28501880168914795
                        },
                        {
                          "X": 0.38197797536849976,
                          "Y": 0.28501880168914795
                        }
                      ]
                    },
                    "Confidence": 73.2164535522461
                  },
                  "PageNumber": 1
                },
                {
                  "Type": {
                    "Text": "EXPENSE_ROW",
                    "Confidence": 78.50700378417969
                  },
                  "ValueDetection": {
                    "Text": "F 1 CVS H/C PATCH SM 5CT 6.99T",
                    "Geometry": {
                      "BoundingBox": {
                        "Width": 0.2870054244995117,
                        "Height": 0.012272562831640244,
                        "Left": 0.3690906763076782,
                        "Top": 0.275200754404068
                      },
                      "Polygon": [
                        {
                          "X": 0.3690906763076782,
                          "Y": 0.275200754404068
                        },
                        {
                          "X": 0.6560961008071899,
                          "Y": 0.275200754404068
                        },
                        {
                          "X": 0.6560961008071899,
                          "Y": 0.28747332096099854
                        },
                        {
                          "X": 0.3690906763076782,
                          "Y": 0.28747332096099854
                        }
                      ]
                    },
                    "Confidence": 77.60138702392578
                  },
                  "PageNumber": 1
                }
              ]
            }
          ]
        }
      ]
    }
  ],
  "ResponseMetadata": {
    "RequestId": "d6420d3d-eda2-4ff2-8aaa-5b6e8eb2beec",
    "HTTPStatusCode": 200,
    "HTTPHeaders": {
      "x-amzn-requestid": "d6420d3d-eda2-4ff2-8aaa-5b6e8eb2beec",
      "content-type": "application/x-amz-json-1.1",
      "content-length": "16209",
      "date": "Mon, 07 Feb 2022 06:37:41 GMT"
    },
    "RetryAttempts": 0
  }
}
